Workbook

Sheet Simulador
C1: SIMULADOR DE OPERACIONES | O1: ticker | P1: =IFERROR(VLOOKUP($F$4,Datos!$A:$K,2,FALSE),0)
C2: Seleccione el instrumento y registre las operaciones del periodo. El volumen y los costos se calculan automáticamente. | O2: digits | P2: =IFERROR(VLOOKUP($F$4,Datos!$A:$K,3,FALSE),0)
O3: contrato | P3: =IFERROR(VLOOKUP($F$4,Datos!$A:$K,4,FALSE),0)
C4: 1 · Instrumento | F4: Dólar / Peso Chileno | I4: Precio de referencia | L4: =$P$7 | O4: clp_unidad | P4: =IFERROR(VLOOKUP($F$4,Datos!$A:$K,5,FALSE),0)
C5: 2 · Capital de la cuenta | F5: 2000000 | I5: Capital mínimo por operación (0,01 lotes) | L5: =0.01*$P$7*$P$4*$P$5 | O5: tasa | P5: =IFERROR(VLOOKUP($F$4,Datos!$A:$K,6,FALSE),0)
I6: Spread vigente al generar | L6: =$P$6 | O6: spread | P6: =IFERROR(VLOOKUP($F$4,Datos!$A:$K,7,FALSE),0)
C7: =IF($F$4="","⚠ Seleccione un instrumento de la lista.",IF(SUMPRODUCT(($E$10:$E$15>0)*($F$10:$F$15=0))>0,"⚠ Hay una operación con capital comprometido y sin precio de entrada.",IF(SUMPRODUCT(($F$10:$F$15>0)*(ABS($F$10:$F$15/$P$7-1)>0.1))>0,"⚠ Un precio de entrada difiere en más de 10% del precio de referencia ($"&FIXED($P$7,$P$2)&"). Verifique que corresponda al instrumento seleccionado.",IF(SUMPRODUCT(($E$10:$E$15>0)*($I$10:$I$15=0))>0,"⚠ Hay una operación bajo el volumen mínimo de 0,01 lotes, que requiere $"&FIXED(0.01*$P$7*$P$4*$P$5,0)&".",IF($L$19>$F$5,"⚠ El margen requerido excede el capital de la cuenta.","✓ "&COUNTIF($I$10:$I$15,">0")&" operación(es) sobre "&$P$1&". El volumen indicado es el que se ingresa en MT5."))))) | O7: precio_ref | P7: =IFERROR(VLOOKUP($F$4,Datos!$A:$K,8,FALSE),0)
C8: OPERACIONES DEL PERIODO · cada fila es una operación independiente, con su fecha, dirección y capital | O8: swap_modo | P8: =IFERROR(VLOOKUP($F$4,Datos!$A:$K,9,FALSE),0)
C9: FECHA | D9: DIRECCIÓN | E9: CAPITAL COMPROMETIDO | F9: PRECIO DE ENTRADA | G9: PRECIO DE SALIDA | H9: DÍAS DE MANTENCIÓN | I9: VOLUMEN (LOTES) | J9: COSTO DE APERTURA | K9: COSTO DE MANTENCIÓN | L9: RESULTADO NETO | M9: OBSERVACIÓN | O9: swap_compra | P9: =IFERROR(VLOOKUP($F$4,Datos!$A:$K,10,FALSE),0)
C10: 46249 | D10: COMPRA | E10: 500000 | F10: 919.5 | G10: 924.5 | H10: 2 | I10: =IFERROR(MAX(0,ROUNDDOWN($E10/($F10*$P$4*$P$5),2)),0) | J10: =IF($I10=0,"",$I10*$P$6*$P$4) | K10: =IF(OR($I10=0,$H10=0),"",ABS(IF($D10="VENTA",$P$10,$P$9)*IF($P$8=1,$I10*POWER(10,-$P$2)*$P$4,$I10*$F10*$P$4/100/360))*($H10+2*ROUNDDOWN($H10/7,0))) | L10: =IF($I10=0,"",IF($D10="COMPRA",$G10-$F10,$F10-$G10)*$I10*$P$4-N($J10)-N($K10)) | M10: =IF(OR($I10=0,$G10=""),"",IF(AND($D10="COMPRA",$G10<$F10),"precio de salida inferior a la entrada: resultado negativo en una compra",IF(AND($D10="VENTA",$G10>$F10),"precio de salida superior a la entrada: resultado negativo en una venta",""))) | O10: swap_venta | P10: =IFERROR(VLOOKUP($F$4,Datos!$A:$K,11,FALSE),0)
C11: 46251 | D11: VENTA | E11: 400000 | F11: 926.5 | G11: 923.5 | H11: 1 | I11: =IFERROR(MAX(0,ROUNDDOWN($E11/($F11*$P$4*$P$5),2)),0) | J11: =IF($I11=0,"",$I11*$P$6*$P$4) | K11: =IF(OR($I11=0,$H11=0),"",ABS(IF($D11="VENTA",$P$10,$P$9)*IF($P$8=1,$I11*POWER(10,-$P$2)*$P$4,$I11*$F11*$P$4/100/360))*($H11+2*ROUNDDOWN($H11/7,0))) | L11: =IF($I11=0,"",IF($D11="COMPRA",$G11-$F11,$F11-$G11)*$I11*$P$4-N($J11)-N($K11)) | M11: =IF(OR($I11=0,$G11=""),"",IF(AND($D11="COMPRA",$G11<$F11),"precio de salida inferior a la entrada: resultado negativo en una compra",IF(AND($D11="VENTA",$G11>$F11),"precio de salida superior a la entrada: resultado negativo en una venta","")))
C12: 46252 | D12: COMPRA | E12: 300000 | F12: 922.5 | G12: 921 | H12: 0 | I12: =IFERROR(MAX(0,ROUNDDOWN($E12/($F12*$P$4*$P$5),2)),0) | J12: =IF($I12=0,"",$I12*$P$6*$P$4) | K12: =IF(OR($I12=0,$H12=0),"",ABS(IF($D12="VENTA",$P$10,$P$9)*IF($P$8=1,$I12*POWER(10,-$P$2)*$P$4,$I12*$F12*$P$4/100/360))*($H12+2*ROUNDDOWN($H12/7,0))) | L12: =IF($I12=0,"",IF($D12="COMPRA",$G12-$F12,$F12-$G12)*$I12*$P$4-N($J12)-N($K12)) | M12: =IF(OR($I12=0,$G12=""),"",IF(AND($D12="COMPRA",$G12<$F12),"precio de salida inferior a la entrada: resultado negativo en una compra",IF(AND($D12="VENTA",$G12>$F12),"precio de salida superior a la entrada: resultado negativo en una venta","")))
I13: =IFERROR(MAX(0,ROUNDDOWN($E13/($F13*$P$4*$P$5),2)),0) | J13: =IF($I13=0,"",$I13*$P$6*$P$4) | K13: =IF(OR($I13=0,$H13=0),"",ABS(IF($D13="VENTA",$P$10,$P$9)*IF($P$8=1,$I13*POWER(10,-$P$2)*$P$4,$I13*$F13*$P$4/100/360))*($H13+2*ROUNDDOWN($H13/7,0))) | L13: =IF($I13=0,"",IF($D13="COMPRA",$G13-$F13,$F13-$G13)*$I13*$P$4-N($J13)-N($K13)) | M13: =IF(OR($I13=0,$G13=""),"",IF(AND($D13="COMPRA",$G13<$F13),"precio de salida inferior a la entrada: resultado negativo en una compra",IF(AND($D13="VENTA",$G13>$F13),"precio de salida superior a la entrada: resultado negativo en una venta","")))
I14: =IFERROR(MAX(0,ROUNDDOWN($E14/($F14*$P$4*$P$5),2)),0) | J14: =IF($I14=0,"",$I14*$P$6*$P$4) | K14: =IF(OR($I14=0,$H14=0),"",ABS(IF($D14="VENTA",$P$10,$P$9)*IF($P$8=1,$I14*POWER(10,-$P$2)*$P$4,$I14*$F14*$P$4/100/360))*($H14+2*ROUNDDOWN($H14/7,0))) | L14: =IF($I14=0,"",IF($D14="COMPRA",$G14-$F14,$F14-$G14)*$I14*$P$4-N($J14)-N($K14)) | M14: =IF(OR($I14=0,$G14=""),"",IF(AND($D14="COMPRA",$G14<$F14),"precio de salida inferior a la entrada: resultado negativo en una compra",IF(AND($D14="VENTA",$G14>$F14),"precio de salida superior a la entrada: resultado negativo en una venta","")))
I15: =IFERROR(MAX(0,ROUNDDOWN($E15/($F15*$P$4*$P$5),2)),0) | J15: =IF($I15=0,"",$I15*$P$6*$P$4) | K15: =IF(OR($I15=0,$H15=0),"",ABS(IF($D15="VENTA",$P$10,$P$9)*IF($P$8=1,$I15*POWER(10,-$P$2)*$P$4,$I15*$F15*$P$4/100/360))*($H15+2*ROUNDDOWN($H15/7,0))) | L15: =IF($I15=0,"",IF($D15="COMPRA",$G15-$F15,$F15-$G15)*$I15*$P$4-N($J15)-N($K15)) | M15: =IF(OR($I15=0,$G15=""),"",IF(AND($D15="COMPRA",$G15<$F15),"precio de salida inferior a la entrada: resultado negativo en una compra",IF(AND($D15="VENTA",$G15>$F15),"precio de salida superior a la entrada: resultado negativo en una venta","")))
C16: TOTALES | E16: =SUM(E10:E15) | I16: =SUM(I10:I15) | J16: =SUM(J10:J15) | K16: =SUM(K10:K15) | L16: =SUM(L10:L15)
I18: Exposición nocional total | L18: =SUMPRODUCT($I$10:$I$15,$F$10:$F$15)*$P$4
I19: Margen requerido (posiciones simultáneas) | L19: =$L$18*$P$5
I20: Resultado neto del periodo | L20: =$L$16
I21: Patrimonio final | L21: =$F$5+$L$16
C23: Especificaciones del broker al 2026-08-19 14:41 hora Chile. Celdas crema: campos editables; el resto son fórmulas. El COSTO DE MANTENCIÓN (swap) es una estimación: agrega 2 días por semana completa, porque el broker aplica cargo triple un día a la semana. Este simulador no incorpora stop loss.

Sheet Datos
A1: INSTRUMENTO | B1: TICKER MT5 | C1: DECIMALES | D1: TAMAÑO DE CONTRATO (1 lote) | E1: VALOR EN CLP DE 1,0 DE PRECIO (POR LOTE) | F1: MARGEN | G1: SPREAD | H1: PRECIO DE REFERENCIA | I1: MODO SWAP | J1: SWAP COMPRA | K1: SWAP VENTA
A2: Dólar / Peso Chileno | B2: USDCLP | C2: 2 | D2: 100000 | E2: 100000 | F2: 0.01 | G2: 1 | H2: 922.5 | I2: 1 | J2: -7 | K2: -0.1
A3: Dólar / Yen Japonés | B3: USDJPY | C3: 3 | D3: 100000 | E3: 579030.62 | F3: 0.010063 | G3: 0.04 | H3: 158.318 | I3: 1 | J3: -2.513 | K3: -3.631
A4: Euro / Dólar | B4: EURUSD | C4: 5 | D4: 100000 | E4: 92250000 | F4: 0.01 | G4: 0.00026 | H4: 1.16742 | I4: 1 | J4: -5.455 | K4: -1.09
A5: Libra / Dólar | B5: GBPUSD | C5: 5 | D5: 100000 | E5: 92250000 | F5: 0.01 | G5: 0.0005 | H5: 1.36083 | I5: 1 | J5: -3.612 | K5: -3.264
A6: Oro | B6: XAUUSD | C6: 2 | D6: 100 | E6: 92150 | F6: 0.045049 | G6: 0.6 | H6: 4490.4 | I6: 1 | J6: -16 | K6: -6
A7: Plata | B7: XAGUSD | C7: 3 | D7: 5000 | E7: 4607500 | F7: 0.045049 | G7: 0.05 | H7: 65.909 | I7: 1 | J7: -4 | K7: -1
A8: Petróleo WTI | B8: WTI.spot | C8: 3 | D8: 1000 | E8: 921500 | F8: 0.015016 | G8: 0.15 | H8: 84.934 | I8: 1 | J8: -20 | K8: -15
A9: Bitcoin | B9: BTCUSD | C9: 2 | D9: 1 | E9: 921.5 | F9: 0.015016 | G9: 79.19 | H9: 68375.5 | I9: 5 | J9: -0.288 | K9: -0.082
A10: Nasdaq 100 | B10: US100.spot | C10: 2 | D10: 1 | E10: 921.5 | F10: 0.050054 | G10: 1 | H10: 29490.82 | I10: 5 | J10: -3.8415 | K10: -1.9899
A11: S&P 500 | B11: US500.spot | C11: 2 | D11: 1 | E11: 921.5 | F11: 0.050054 | G11: 1 | H11: 7729.78 | I11: 5 | J11: -3.8415 | K11: -1.9899
A12: Dow Jones Industrial | B12: US30.spot | C12: 2 | D12: 1 | E12: 921.5 | F12: 0.050054 | G12: 7 | H12: 53522.5 | I12: 5 | J12: -3.6161 | K12: -1.9353
A13: Apple Inc. | B13: #AAPL | C13: 2 | D13: 50 | E13: 46075 | F13: 0.005005 | G13: 0.32 | H13: 315.18 | I13: 5 | J13: -5.1 | K13: -5.1
... A26: Deere & Co. | B26: #DE | C26: 2 | D26: 50 | E26: 46075 | F26: 0.005005 | G26: 0.77 | H26: 587.1 | I26: 5 | J26: -5.1 | K26: -5.1
A28: Actualizado desde MT5 (cuenta 51142, CLP) el 2026-08-19 14:41 hora Chile. No editar a mano: se regenera con scripts/simulador_gi.py. MODO SWAP 1 = puntos por día por lote; 5 = interés anual sobre el nocional (año de 360 días).
