Workbook

Sheet Simulador
C1: SIMULADOR DE OPERACIONES | Q1: ticker | R1: =IFERROR(VLOOKUP($F$4,Datos!$A:$N,2,FALSE),0)
C2: Se escribe el volumen en lotes, la unidad del terminal. La planilla calcula el margen que bloquea, el apalancamiento y los costos. | Q2: digits | R2: =IFERROR(VLOOKUP($F$4,Datos!$A:$N,3,FALSE),0)
Q3: contrato | R3: =IFERROR(VLOOKUP($F$4,Datos!$A:$N,4,FALSE),0)
C4: 1 · Instrumento | F4: Dólar / Peso Chileno | J4: Precio de referencia | M4: =$R$7 | Q4: clp_unidad | R4: =IFERROR(VLOOKUP($F$4,Datos!$A:$N,5,FALSE),0)
C5: 2 · Capital de la cuenta | F5: 2000000 | J5: ="Capital mínimo ("&FIXED($R$13,2)&" lotes)" | M5: =$R$13*$R$7*$R$4*$R$5 | Q5: tasa | R5: =IFERROR(VLOOKUP($F$4,Datos!$A:$N,6,FALSE),0)
J6: Spread vigente al generar | M6: =$R$6 | Q6: spread | R6: =IFERROR(VLOOKUP($F$4,Datos!$A:$N,7,FALSE),0)
C7: =IF($F$4="","⚠ Seleccione un instrumento de la lista.",IF(SUMPRODUCT(--ISTEXT($D$11:$D$16))+SUMPRODUCT(--ISTEXT($G$11:$H$16))+SUMPRODUCT(--ISTEXT($I$11:$I$16))>0,"⚠ Hay un valor escrito como texto. El separador decimal de este Excel es la coma: escriba 0,54 y no 0.54.",IF(SUMPRODUCT(($D$11:$D$16>0)*($G$11:$G$16=0))>0,"⚠ Hay una operación con volumen y sin precio de entrada.",IF(SUMPRODUCT(($G$11:$G$16>0)*(ABS($G$11:$G$16/$R$7-1)>0.1))>0,"⚠ Un precio de entrada difiere en más de 10% del precio de referencia ($"&FIXED($R$7,$R$2)&"). Verifique que corresponda al instrumento seleccionado.",IF(IFERROR(SUMPRODUCT(($D$11:$D$16>0)*(($D$11:$D$16<$R$13)+(MOD(ROUND($D$11:$D$16/$R$14,6),1)<>0)))>0,FALSE),"⚠ Hay un volumen inválido para este instrumento: el mínimo es "&FIXED($R$13,2)&" lotes y debe ir en múltiplos de "&FIXED($R$14,2)&".",IF($M$21>$F$5,"⚠ El margen requerido excede el capital de la cuenta.","✓ "&COUNTIF($D$11:$D$16,">0")&" operación(es) sobre "&$R$1&". El volumen en lotes es el que se ingresa en MT5.")))))) | Q7: precio_ref | R7: =IFERROR(VLOOKUP($F$4,Datos!$A:$N,8,FALSE),0)
Q8: swap_modo | R8: =IFERROR(VLOOKUP($F$4,Datos!$A:$N,9,FALSE),0)
C9: SIMULACIÓN | K9: COSTOS | Q9: swap_compra | R9: =IFERROR(VLOOKUP($F$4,Datos!$A:$N,10,FALSE),0)
C10: DIRECCIÓN | D10: VOLUMEN EN LOTES | E10: MARGEN REQUERIDO | F10: APALANCAMIENTO (VECES) | G10: PRECIO DE ENTRADA | H10: PRECIO DE SALIDA | I10: DÍAS ABIERTA | J10: RESULTADO BRUTO | K10: COSTO DE APERTURA (SPREAD) | L10: COSTO DE MANTENCIÓN (SWAP) | M10: RESULTADO NETO | N10: OBSERVACIÓN | Q10: swap_venta | R10: =IFERROR(VLOOKUP($F$4,Datos!$A:$N,11,FALSE),0)
C11: COMPRA | D11: 0.54 | E11: =IF($D11=0,"",$D11*$G11*$R$4*$R$5) | F11: =IF(OR($D11=0,$F$5=0),"",$D11*$G11*$R$4/$F$5) | G11: 924.7 | H11: 929.7 | I11: 2 | J11: =IF(OR($D11=0,$H11=0),"",IF($C11="COMPRA",$H11-$G11,$G11-$H11)*$D11*$R$4) | K11: =IF($D11=0,"",$D11*$R$6*$R$4) | L11: =IF(OR($D11=0,$I11=0),"",-IF($C11="VENTA",$R$10,$R$9)*IF($R$8=1,$D11*POWER(10,-$R$2)*$R$4,$D11*$G11*$R$4/100/360)*$I11) | M11: =IF($D11=0,"",N($J11)-N($K11)-N($L11)) | N11: =IF(OR($D11=0,$H11=0),"",IF(AND($C11="COMPRA",$H11<$G11),"precio de salida inferior a la entrada: resultado negativo en una compra",IF(AND($C11="VENTA",$H11>$G11),"precio de salida superior a la entrada: resultado negativo en una venta",""))) | Q11: llamada_margen | R11: 200
C12: VENTA | D12: 0.43 | E12: =IF($D12=0,"",$D12*$G12*$R$4*$R$5) | F12: =IF(OR($D12=0,$F$5=0),"",$D12*$G12*$R$4/$F$5) | G12: 931.7 | H12: 928.7 | I12: 1 | J12: =IF(OR($D12=0,$H12=0),"",IF($C12="COMPRA",$H12-$G12,$G12-$H12)*$D12*$R$4) | K12: =IF($D12=0,"",$D12*$R$6*$R$4) | L12: =IF(OR($D12=0,$I12=0),"",-IF($C12="VENTA",$R$10,$R$9)*IF($R$8=1,$D12*POWER(10,-$R$2)*$R$4,$D12*$G12*$R$4/100/360)*$I12) | M12: =IF($D12=0,"",N($J12)-N($K12)-N($L12)) | N12: =IF(OR($D12=0,$H12=0),"",IF(AND($C12="COMPRA",$H12<$G12),"precio de salida inferior a la entrada: resultado negativo en una compra",IF(AND($C12="VENTA",$H12>$G12),"precio de salida superior a la entrada: resultado negativo en una venta",""))) | Q12: cierre_forzado | R12: 50
C13: COMPRA | D13: 0.32 | E13: =IF($D13=0,"",$D13*$G13*$R$4*$R$5) | F13: =IF(OR($D13=0,$F$5=0),"",$D13*$G13*$R$4/$F$5) | G13: 927.7 | H13: 926.2 | I13: 0 | J13: =IF(OR($D13=0,$H13=0),"",IF($C13="COMPRA",$H13-$G13,$G13-$H13)*$D13*$R$4) | K13: =IF($D13=0,"",$D13*$R$6*$R$4) | L13: =IF(OR($D13=0,$I13=0),"",-IF($C13="VENTA",$R$10,$R$9)*IF($R$8=1,$D13*POWER(10,-$R$2)*$R$4,$D13*$G13*$R$4/100/360)*$I13) | M13: =IF($D13=0,"",N($J13)-N($K13)-N($L13)) | N13: =IF(OR($D13=0,$H13=0),"",IF(AND($C13="COMPRA",$H13<$G13),"precio de salida inferior a la entrada: resultado negativo en una compra",IF(AND($C13="VENTA",$H13>$G13),"precio de salida superior a la entrada: resultado negativo en una venta",""))) | Q13: vol_min | R13: =IFERROR(VLOOKUP($F$4,Datos!$A:$N,12,FALSE),0)
E14: =IF($D14=0,"",$D14*$G14*$R$4*$R$5) | F14: =IF(OR($D14=0,$F$5=0),"",$D14*$G14*$R$4/$F$5) | J14: =IF(OR($D14=0,$H14=0),"",IF($C14="COMPRA",$H14-$G14,$G14-$H14)*$D14*$R$4) | K14: =IF($D14=0,"",$D14*$R$6*$R$4) | L14: =IF(OR($D14=0,$I14=0),"",-IF($C14="VENTA",$R$10,$R$9)*IF($R$8=1,$D14*POWER(10,-$R$2)*$R$4,$D14*$G14*$R$4/100/360)*$I14) | M14: =IF($D14=0,"",N($J14)-N($K14)-N($L14)) | N14: =IF(OR($D14=0,$H14=0),"",IF(AND($C14="COMPRA",$H14<$G14),"precio de salida inferior a la entrada: resultado negativo en una compra",IF(AND($C14="VENTA",$H14>$G14),"precio de salida superior a la entrada: resultado negativo en una venta",""))) | Q14: vol_paso | R14: =IFERROR(VLOOKUP($F$4,Datos!$A:$N,13,FALSE),0)
E15: =IF($D15=0,"",$D15*$G15*$R$4*$R$5) | F15: =IF(OR($D15=0,$F$5=0),"",$D15*$G15*$R$4/$F$5) | J15: =IF(OR($D15=0,$H15=0),"",IF($C15="COMPRA",$H15-$G15,$G15-$H15)*$D15*$R$4) | K15: =IF($D15=0,"",$D15*$R$6*$R$4) | L15: =IF(OR($D15=0,$I15=0),"",-IF($C15="VENTA",$R$10,$R$9)*IF($R$8=1,$D15*POWER(10,-$R$2)*$R$4,$D15*$G15*$R$4/100/360)*$I15) | M15: =IF($D15=0,"",N($J15)-N($K15)-N($L15)) | N15: =IF(OR($D15=0,$H15=0),"",IF(AND($C15="COMPRA",$H15<$G15),"precio de salida inferior a la entrada: resultado negativo en una compra",IF(AND($C15="VENTA",$H15>$G15),"precio de salida superior a la entrada: resultado negativo en una venta","")))
E16: =IF($D16=0,"",$D16*$G16*$R$4*$R$5) | F16: =IF(OR($D16=0,$F$5=0),"",$D16*$G16*$R$4/$F$5) | J16: =IF(OR($D16=0,$H16=0),"",IF($C16="COMPRA",$H16-$G16,$G16-$H16)*$D16*$R$4) | K16: =IF($D16=0,"",$D16*$R$6*$R$4) | L16: =IF(OR($D16=0,$I16=0),"",-IF($C16="VENTA",$R$10,$R$9)*IF($R$8=1,$D16*POWER(10,-$R$2)*$R$4,$D16*$G16*$R$4/100/360)*$I16) | M16: =IF($D16=0,"",N($J16)-N($K16)-N($L16)) | N16: =IF(OR($D16=0,$H16=0),"",IF(AND($C16="COMPRA",$H16<$G16),"precio de salida inferior a la entrada: resultado negativo en una compra",IF(AND($C16="VENTA",$H16>$G16),"precio de salida superior a la entrada: resultado negativo en una venta","")))
C17: TOTALES | D17: =SUM(D11:D16) | E17: =SUM(E11:E16) | F17: =SUM(F11:F16) | J17: =SUM(J11:J16) | K17: =SUM(K11:K16) | L17: =SUM(L11:L16) | M17: =SUM(M11:M16)
J19: Monto total controlado | M19: =SUMPRODUCT($D$11:$D$16,$G$11:$G$16)*$R$4
J20: Apalancamiento total | M20: =$F$17
J21: Margen requerido (posiciones simultáneas) | M21: =$M$19*$R$5
J22: Nivel de margen al abrir | M22: =IF($M$21=0,"",100*$F$5/$M$21)
J23: Recorrido adverso hasta el cierre forzado | M23: =IF(OR($M$21=0,SUMPRODUCT((($C$11:$C$16="COMPRA")*2-1)*$D$11:$D$16)=0),"",MAX(0,ROUND(($F$5-$R$12/100*$M$21)/ABS(SUMPRODUCT((($C$11:$C$16="COMPRA")*2-1)*$D$11:$D$16)*$R$4),$R$2)))
J24: Resultado neto del periodo | M24: =$M$17
J25: Patrimonio final | M25: =$F$5+$M$17
C27: Especificaciones de la cuenta real del broker al 2026-09-09 15:08 hora Chile. Celdas crema: campos editables; el resto son fórmulas. El volumen en lotes se escribe en múltiplos del paso que acepta MT5 en ese instrumento, indicado arriba a la derecha. APALANCAMIENTO son las veces que el capital de la cuenta queda controlado por esa operación, y la columna es aditiva: su total es el apalancamiento del periodo. El COSTO DE MANTENCIÓN (SWAP) se estima por días calendario. El broker avisa cuando el nivel de margen baja de 200% y cierra posiciones por su cuenta en 50%, que es el umbral contra el que se mide el recorrido. Este simulador no incorpora stop loss.

Sheet Datos
A1: INSTRUMENTO | B1: TICKER MT5 | C1: DECIMALES | D1: TAMAÑO DE CONTRATO (1 lote) | E1: VALOR EN CLP DE 1,0 DE PRECIO (POR LOTE) | F1: MARGEN | G1: SPREAD | H1: PRECIO DE REFERENCIA | I1: MODO SWAP | J1: SWAP COMPRA | K1: SWAP VENTA | L1: VOLUMEN MÍNIMO | M1: PASO DE VOLUMEN | N1: GRUPO
A2: Australian Dollar vs Canadian Dollar | B2: AUDCAD | C2: 5 | D2: 100000 | E2: 67222202 | F2: 0.009999 | G2: 0.0004 | H2: 0.99701 | I2: 1 | J2: -2.31 | K2: -9.139 | L2: 0.01 | M2: 0.01 | N2: FX
A3: Australian Dollar vs Japanese Yen | B3: AUDJPY | C3: 3 | D3: 100000 | E3: 604431.76 | F3: 0.009998 | G3: 0.07 | H3: 110.898 | I3: 1 | J3: -2.014 | K3: -14.365 | L3: 0.01 | M3: 0.01 | N3: FX
A4: Australian Dollar vs New Zealand Dollar | B4: AUDNZD | C4: 5 | D4: 100000 | E4: 54227776 | F4: 0.009996 | G4: 0.0006 | H4: 1.23638 | I4: 1 | J4: -3.164 | K4: -10.686 | L4: 0.01 | M4: 0.01 | N4: FX
A5: Australian Dollar vs Swiss Franc | B5: AUDCHF | C5: 5 | D5: 100000 | E5: 1.1462568e+08 | F5: 0.009991 | G5: 0.0009 | H5: 0.58515 | I5: 1 | J5: -0.253 | K5: -11.128 | L5: 0.01 | M5: 0.01 | N5: FX
A6: Australian Dollar vs US Dollar | B6: AUDUSD | C6: 5 | D6: 100000 | E6: 92770000 | F6: 0.01 | G6: 0.00032 | H6: 0.72239 | I6: 1 | J6: -2.206 | K6: -1.285 | L6: 0.01 | M6: 0.01 | N6: FX
A7: British Pounds vs. New Zealand Dollar | B7: GBPNZD | C7: 5 | D7: 100000 | E7: 54227776 | F7: 0.019982 | G7: 0.003 | H7: 2.32201 | I7: 1 | J7: -5.185 | K7: -22.75 | L7: 0.01 | M7: 0.01 | N7: FX
A8: British Pounds vs Australian Dollar | B8: GBPAUD | C8: 5 | D8: 100000 | E8: 67016120 | F8: 0.009997 | G8: 0.0009 | H8: 1.87777 | I8: 1 | J8: -9.022 | K8: -7.371 | L8: 0.01 | M8: 0.01 | N8: FX
A9: British Pounds vs Canadian Dollar | B9: GBPCAD | C9: 5 | D9: 100000 | E9: 67222202 | F9: 0.009998 | G9: 0.0009 | H9: 1.87178 | I9: 1 | J9: -3.7 | K9: -19.11 | L9: 0.01 | M9: 0.01 | N9: FX
A10: British Pounds vs Japanese Yen | B10: GBPJPY | C10: 3 | D10: 100000 | E10: 604431.76 | F10: 0.009999 | G10: 0.08 | H10: 208.164 | I10: 1 | J10: -3.222 | K10: -28.652 | L10: 0.01 | M10: 0.01 | N10: FX
A11: British Pounds vs Swiss Franc | B11: GBPCHF | C11: 5 | D11: 100000 | E11: 1.1462568e+08 | F11: 0.009995 | G11: 0.0008 | H11: 1.09806 | I11: 1 | J11: -0.087 | K11: -24.531 | L11: 0.01 | M11: 0.01 | N11: FX
A12: Canadian Dollar vs Japanese Yen | B12: CADJPY | C12: 3 | D12: 100000 | E12: 604431.76 | F12: 0.009998 | G12: 0.05 | H12: 111.243 | I12: 1 | J12: -1.201 | K12: -8.281 | L12: 0.01 | M12: 0.01 | N12: FX
A13: Canadian Dollar vs Swiss Franc | B13: CADCHF | C13: 5 | D13: 100000 | E13: 1.1462568e+08 | F13: 0.009991 | G13: 0.00075 | H13: 0.58695 | I13: 1 | J13: 0.507 | K13: -7.852 | L13: 0.01 | M13: 0.01 | N13: FX
... A149: Walt Disney Co. | B149: #DIS | C149: 2 | D149: 1 | E149: 927.3 | F149: 0.002501 | G149: 0.5 | H149: 104.97 | I149: 5 | J149: -5.1 | K149: -5.1 | L149: 0.1 | M149: 0.1 | N149: CFD Acciones
A151: Especificaciones tomadas de la cuenta 51492 de MT5, GrupoInteligenciaSpA-Server, tipo REAL, en CLP, el 2026-09-09 15:08 hora Chile. No editar a mano: se regenera con scripts/simulador_gi.py. MODO SWAP 1 = puntos por día por lote; 5 = interés anual sobre el nocional (año de 360 días). Los nombres en español son los del catálogo del grupo de análisis; el resto llega con la descripción del broker.
